{"cameraMode":{"drawMode":0,"name":"Shaded","section":"Shading Mode"},"sceneLighting":false,"audioPlay":false,"sceneViewState":{"m_AlwaysRefresh":false,"showFog":true,"showSkybox":false,"showFlares":true,"showImageEffects":true,"showParticleSystems":true,"showVisualEffectGraphs":true,"m_FxEnabled":true},"in2DMode":false,"pivot":{"x":0.4471050500869751,"y":-0.1975235939025879,"z":11.522294998168946},"rotation":{"x":0.024096166715025903,"y":-0.967978298664093,"z":0.10231669992208481,"w":0.2279646098613739},"size":0.8495909571647644,"orthographic":false}